hardware/LFSR.v
module LFSR #(
    parameter DATA_WIDTH = 16,
    parameter MAX_PERIOD = 65535, // 2^16 - 1
    parameter LOG2_DATA_WIDTH = 4
    // primitive polimonials to be changed as DATA_WIDTH changes // xor_data
)
(
    input clk,
    input rst,
    input [DATA_WIDTH-1:0] seed_in,
    input seed_valid,
 
    output [DATA_WIDTH-1:0] random_number,
    output random_number_valid
);
    parameter IDLE = 0, EXECUTE = 1, LAST = 2;

    reg [1:0] state;
    reg [DATA_WIDTH-1:0] random_number_cnt;
    // reg [$log2(DATA_WIDTH)-1:0] shift_cnt;
    reg [LOG2_DATA_WIDTH-1:0] shift_cnt;
    reg [DATA_WIDTH-1:0] data;
    wire xor_data;

    always @(posedge clk or posedge rst) begin
        if(rst) begin
            state <= IDLE;
        end
        else begin
            case(state)
            IDLE: begin
                if(seed_valid) state <= EXECUTE;
            end
            EXECUTE: begin
                if(random_number_cnt >= MAX_PERIOD - 1) begin
                    state <= LAST;
                end
            end
            LAST: begin
                state <= IDLE;
            end
            endcase 
        end
    end

    always @(posedge clk or posedge rst) begin
        if(rst) begin
            random_number_cnt <= 0;
        end
        else if(state == EXECUTE) begin
            if(random_number_cnt >= MAX_PERIOD - 1) random_number_cnt <= 0;
            else random_number_cnt <= random_number_cnt + 1;
        end
    end
    
    assign xor_data = data[0] + data[1] + data[3] + data[12]; // 16 bits primitive polynomial

    always @(posedge clk or posedge rst) begin
        if (rst) begin
            shift_cnt <= 0;
            data <= 0;
        end
        else begin
            if(state == IDLE && seed_valid) begin
                data <= seed_in;
            end
            else if(state == EXECUTE) begin
                shift_cnt <= shift_cnt + 1; // overflow makes it 0

                data[DATA_WIDTH-2:0] <= data[DATA_WIDTH-1:1];
                data[DATA_WIDTH-1] <= xor_data;
            end
        end
    end

    assign random_number = data;
    assign random_number_valid = (state == EXECUTE) && (shift_cnt == 0);
endmodule

hardware/tb_LFSR.v

module tb_LFSR;
    parameter DATA_WIDTH = 16;
    integer file;

    reg clk;
    reg rst;
    reg [DATA_WIDTH-1:0] seed_in;
    reg seed_valid;
    wire [DATA_WIDTH-1:0] random_number;
    wire random_number_valid;
    reg [DATA_WIDTH-1:0] random_number_array[9:0];
    reg [3:0] cnt;

    LFSR u_LFSR (
        .clk(clk), 
        .rst(rst), 
        .seed_in(seed_in),
        .seed_valid(seed_valid),
        .random_number(random_number),
        .random_number_valid(random_number_valid)
        );

    always #5 clk = ~clk;

    initial begin
        clk = 0;
        rst = 1;
        #10 rst = 0;
        #10 
        seed_in = 16'hffff;
        seed_valid = 1;
        #8 seed_valid = 0;

        wait(cnt == 10);
        file = $fopen("output.bin", "wb");
        if (!file) begin
            $display("Error: Could not open file.");
            $finish;
        end
        for (integer i = 0; i < 10; i = i + 1) begin
            $fdisplay(file, "%b", random_number_array[i]);
        end
        // $fwrite(file, "%b", random_number_array);
        $fclose(file);
        $display("Binary data written to output.bin.");
        $finish;
    end
    always @(posedge clk or posedge rst) begin
        if(rst) begin
            cnt <= 0;
        end
        else begin
            if(random_number_valid) begin
                cnt <= cnt + 1;
                random_number_array[cnt] <= random_number;
            end
        end
    end

    initial begin
        $dumpfile("waveform.vcd");
        $dumpvars(0, tb_LFSR);
    end
endmodule

waveform.vcd
$date
	Tue Jan 28 02:07:36 2025
$end
$version
	Icarus Verilog
$end
$timescale
	1s
$end
$scope module tb_LFSR $end
$var wire 1 ! random_number_valid $end
$var wire 16 " random_number [15:0] $end
$var parameter 32 # DATA_WIDTH $end
$var reg 1 $ clk $end
$var reg 4 % cnt [3:0] $end
$var reg 1 & rst $end
$var reg 16 ' seed_in [15:0] $end
$var reg 1 ( seed_valid $end
$var integer 32 ) file [31:0] $end
$scope module u_LFSR $end
$var wire 1 $ clk $end
$var wire 16 * random_number [15:0] $end
$var wire 1 ! random_number_valid $end
$var wire 1 & rst $end
$var wire 16 + seed_in [15:0] $end
$var wire 1 ( seed_valid $end
$var wire 1 , xor_data $end
$var parameter 32 - DATA_WIDTH $end
$var parameter 32 . EXECUTE $end
$var parameter 32 / IDLE $end
$var parameter 32 0 LAST $end
$var parameter 32 1 LOG2_DATA_WIDTH $end
$var parameter 32 2 MAX_PERIOD $end
$var reg 16 3 data [15:0] $end
$var reg 16 4 random_number_cnt [15:0] $end
$var reg 4 5 shift_cnt [3:0] $end
$var reg 2 6 state [1:0] $end
$upscope $end
$scope begin $ivl_for_loop0 $end
$var integer 32 7 i [31:0] $end
$upscope $end
$upscope $end
$enddefinitions $end
$comment Show the parameter values. $end
$dumpall
b1111111111111111 2
b100 1
b10 0
b0 /
b1 .
b10000 -
b10000 #
$end
#0
$dumpvars
bx 7
b0 6
b0 5
b0 4
b0 3
0,
bx +
b0 *
bx )
x(
bx '
1&
bx %
0$
b0 "
0!
$end
#5
b0 %
1$
#10
0$
0&
#15
1$
#20
0$
1(
b1111111111111111 '
b1111111111111111 +
#25
0,
1!
b1111111111111111 "
b1111111111111111 *
b1111111111111111 3
b1 6
1$
#28
0(
#30
0$
#35
0!
b1 4
b111111111111111 "
b111111111111111 *
b111111111111111 3
b1 5
b1 %
1$
#40
0$
#45
b11111111111111 "
b11111111111111 *
b11111111111111 3
b10 5
b10 4
1$
#50
0$
#55
b11 4
b1111111111111 "
b1111111111111 *
b1111111111111 3
b11 5
1$
#60
0$
#65
1,
b111111111111 "
b111111111111 *
b111111111111 3
b100 5
b100 4
1$
#70
0$
#75
b101 4
b1000011111111111 "
b1000011111111111 *
b1000011111111111 3
b101 5
1$
#80
0$
#85
b1100001111111111 "
b1100001111111111 *
b1100001111111111 3
b110 5
b110 4
1$
#90
0$
#95
b111 4
b1110000111111111 "
b1110000111111111 *
b1110000111111111 3
b111 5
1$
#100
0$
#105
0,
b1111000011111111 "
b1111000011111111 *
b1111000011111111 3
b1000 5
b1000 4
1$
#110
0$
#115
b1001 4
b111100001111111 "
b111100001111111 *
b111100001111111 3
b1001 5
1$
#120
0$
#125
b11110000111111 "
b11110000111111 *
b11110000111111 3
b1010 5
b1010 4
1$
#130
0$
#135
b1011 4
b1111000011111 "
b1111000011111 *
b1111000011111 3
b1011 5
1$
#140
0$
#145
1,
b111100001111 "
b111100001111 *
b111100001111 3
b1100 5
b1100 4
1$
#150
0$
#155
0,
b1101 4
b1000011110000111 "
b1000011110000111 *
b1000011110000111 3
b1101 5
1$
#160
0$
#165
b100001111000011 "
b100001111000011 *
b100001111000011 3
b1110 5
b1110 4
1$
#170
0$
#175
1,
b1111 4
b10000111100001 "
b10000111100001 *
b10000111100001 3
b1111 5
1$
#180
0$
#185
1,
1!
b1001000011110000 "
b1001000011110000 *
b1001000011110000 3
b0 5
b10000 4
1$
#190
0$
#195
1,
0!
b10001 4
b1100100001111000 "
b1100100001111000 *
b1100100001111000 3
b1 5
b10 %
1$
#200
0$
#205
b1110010000111100 "
b1110010000111100 *
b1110010000111100 3
b10 5
b10010 4
1$
#210
0$
#215
1,
b10011 4
b1111001000011110 "
b1111001000011110 *
b1111001000011110 3
b11 5
1$
#220
0$
#225
0,
b1111100100001111 "
b1111100100001111 *
b1111100100001111 3
b100 5
b10100 4
1$
#230
0$
#235
1,
b10101 4
b111110010000111 "
b111110010000111 *
b111110010000111 3
b101 5
1$
#240
0$
#245
b1011111001000011 "
b1011111001000011 *
b1011111001000011 3
b110 5
b10110 4
1$
#250
0$
#255
0,
b10111 4
b1101111100100001 "
b1101111100100001 *
b1101111100100001 3
b111 5
1$
#260
0$
#265
0,
b110111110010000 "
b110111110010000 *
b110111110010000 3
b1000 5
b11000 4
1$
#270
0$
#275
0,
b11001 4
b11011111001000 "
b11011111001000 *
b11011111001000 3
b1001 5
1$
#280
0$
#285
1,
b1101111100100 "
b1101111100100 *
b1101111100100 3
b1010 5
b11010 4
1$
#290
0$
#295
1,
b11011 4
b1000110111110010 "
b1000110111110010 *
b1000110111110010 3
b1011 5
1$
#300
0$
#305
0,
b1100011011111001 "
b1100011011111001 *
b1100011011111001 3
b1100 5
b11100 4
1$
#310
0$
#315
1,
b11101 4
b110001101111100 "
b110001101111100 *
b110001101111100 3
b1101 5
1$
#320
0$
#325
1,
b1011000110111110 "
b1011000110111110 *
b1011000110111110 3
b1110 5
b11110 4
1$
#330
0$
#335
0,
b11111 4
b1101100011011111 "
b1101100011011111 *
b1101100011011111 3
b1111 5
1$
#340
0$
#345
1,
1!
b110110001101111 "
b110110001101111 *
b110110001101111 3
b0 5
b100000 4
1$
#350
0$
#355
1,
0!
b100001 4
b1011011000110111 "
b1011011000110111 *
b1011011000110111 3
b1 5
b11 %
1$
#360
0$
#365
0,
b1101101100011011 "
b1101101100011011 *
b1101101100011011 3
b10 5
b100010 4
1$
#370
0$
#375
0,
b100011 4
b110110110001101 "
b110110110001101 *
b110110110001101 3
b11 5
1$
#380
0$
#385
0,
b11011011000110 "
b11011011000110 *
b11011011000110 3
b100 5
b100100 4
1$
#390
0$
#395
1,
b100101 4
b1101101100011 "
b1101101100011 *
b1101101100011 3
b101 5
1$
#400
0$
#405
1,
b1000110110110001 "
b1000110110110001 *
b1000110110110001 3
b110 5
b100110 4
1$
#410
0$
#415
1,
b100111 4
b1100011011011000 "
b1100011011011000 *
b1100011011011000 3
b111 5
1$
#420
0$
#425
b1110001101101100 "
b1110001101101100 *
b1110001101101100 3
b1000 5
b101000 4
1$
#430
0$
#435
0,
b101001 4
b1111000110110110 "
b1111000110110110 *
b1111000110110110 3
b1001 5
1$
#440
0$
#445
0,
b111100011011011 "
b111100011011011 *
b111100011011011 3
b1010 5
b101010 4
1$
#450
0$
#455
1,
b101011 4
b11110001101101 "
b11110001101101 *
b11110001101101 3
b1011 5
1$
#460
0$
#465
0,
b1001111000110110 "
b1001111000110110 *
b1001111000110110 3
b1100 5
b101100 4
1$
#470
0$
#475
1,
b101101 4
b100111100011011 "
b100111100011011 *
b100111100011011 3
b1101 5
1$
#480
0$
#485
0,
b1010011110001101 "
b1010011110001101 *
b1010011110001101 3
b1110 5
b101110 4
1$
#490
0$
#495
0,
b101111 4
b101001111000110 "
b101001111000110 *
b101001111000110 3
b1111 5
1$
#500
0$
#505
0,
1!
b10100111100011 "
b10100111100011 *
b10100111100011 3
b0 5
b110000 4
1$
#510
0$
#515
0,
0!
b110001 4
b1010011110001 "
b1010011110001 *
b1010011110001 3
b1 5
b100 %
1$
#520
0$
#525
1,
b101001111000 "
b101001111000 *
b101001111000 3
b10 5
b110010 4
1$
#530
0$
#535
b110011 4
b1000010100111100 "
b1000010100111100 *
b1000010100111100 3
b11 5
1$
#540
0$
#545
0,
b1100001010011110 "
b1100001010011110 *
b1100001010011110 3
b100 5
b110100 4
1$
#550
0$
#555
1,
b110101 4
b110000101001111 "
b110000101001111 *
b110000101001111 3
b101 5
1$
#560
0$
#565
1,
b1011000010100111 "
b1011000010100111 *
b1011000010100111 3
b110 5
b110110 4
1$
#570
0$
#575
b110111 4
b1101100001010011 "
b1101100001010011 *
b1101100001010011 3
b111 5
1$
#580
0$
#585
0,
b1110110000101001 "
b1110110000101001 *
b1110110000101001 3
b1000 5
b111000 4
1$
#590
0$
#595
1,
b111001 4
b111011000010100 "
b111011000010100 *
b111011000010100 3
b1001 5
1$
#600
0$
#605
1,
b1011101100001010 "
b1011101100001010 *
b1011101100001010 3
b1010 5
b111010 4
1$
#610
0$
#615
0,
b111011 4
b1101110110000101 "
b1101110110000101 *
b1101110110000101 3
b1011 5
1$
#620
0$
#625
1,
b110111011000010 "
b110111011000010 *
b110111011000010 3
b1100 5
b111100 4
1$
#630
0$
#635
0,
b111101 4
b1011011101100001 "
b1011011101100001 *
b1011011101100001 3
b1101 5
1$
#640
0$
#645
1,
b101101110110000 "
b101101110110000 *
b101101110110000 3
b1110 5
b111110 4
1$
#650
0$
#655
1,
b111111 4
b1010110111011000 "
b1010110111011000 *
b1010110111011000 3
b1111 5
1$
#660
0$
#665
0,
1!
b1101011011101100 "
b1101011011101100 *
b1101011011101100 3
b0 5
b1000000 4
1$
#670
0$
#675
1,
0!
b1000001 4
b110101101110110 "
b110101101110110 *
b110101101110110 3
b1 5
b101 %
1$
#680
0$
#685
0,
b1011010110111011 "
b1011010110111011 *
b1011010110111011 3
b10 5
b1000010 4
1$
#690
0$
#695
1,
b1000011 4
b101101011011101 "
b101101011011101 *
b101101011011101 3
b11 5
1$
#700
0$
#705
0,
b1010110101101110 "
b1010110101101110 *
b1010110101101110 3
b100 5
b1000100 4
1$
#710
0$
#715
1,
b1000101 4
b101011010110111 "
b101011010110111 *
b101011010110111 3
b101 5
1$
#720
0$
#725
1,
b1010101101011011 "
b1010101101011011 *
b1010101101011011 3
b110 5
b1000110 4
1$
#730
0$
#735
1,
b1000111 4
b1101010110101101 "
b1101010110101101 *
b1101010110101101 3
b111 5
1$
#740
0$
#745
1,
b1110101011010110 "
b1110101011010110 *
b1110101011010110 3
b1000 5
b1001000 4
1$
#750
0$
#755
0,
b1001001 4
b1111010101101011 "
b1111010101101011 *
b1111010101101011 3
b1001 5
1$
#760
0$
#765
0,
b111101010110101 "
b111101010110101 *
b111101010110101 3
b1010 5
b1001010 4
1$
#770
0$
#775
1,
b1001011 4
b11110101011010 "
b11110101011010 *
b11110101011010 3
b1011 5
1$
#780
0$
#785
1,
b1001111010101101 "
b1001111010101101 *
b1001111010101101 3
b1100 5
b1001100 4
1$
#790
0$
#795
1,
b1001101 4
b1100111101010110 "
b1100111101010110 *
b1100111101010110 3
b1101 5
1$
#800
0$
#805
1,
b1110011110101011 "
b1110011110101011 *
b1110011110101011 3
b1110 5
b1001110 4
1$
#810
0$
#815
0,
b1001111 4
b1111001111010101 "
b1111001111010101 *
b1111001111010101 3
b1111 5
1$
#820
0$
#825
1,
1!
b111100111101010 "
b111100111101010 *
b111100111101010 3
b0 5
b1010000 4
1$
#830
0$
#835
0,
0!
b1010001 4
b1011110011110101 "
b1011110011110101 *
b1011110011110101 3
b1 5
b110 %
1$
#840
0$
#845
1,
b101111001111010 "
b101111001111010 *
b101111001111010 3
b10 5
b1010010 4
1$
#850
0$
#855
0,
b1010011 4
b1010111100111101 "
b1010111100111101 *
b1010111100111101 3
b11 5
1$
#860
0$
#865
1,
b101011110011110 "
b101011110011110 *
b101011110011110 3
b100 5
b1010100 4
1$
#870
0$
#875
1,
b1010101 4
b1010101111001111 "
b1010101111001111 *
b1010101111001111 3
b101 5
1$
#880
0$
#885
1,
b1101010111100111 "
b1101010111100111 *
b1101010111100111 3
b110 5
b1010110 4
1$
#890
0$
#895
0,
b1010111 4
b1110101011110011 "
b1110101011110011 *
b1110101011110011 3
b111 5
1$
#900
0$
#905
1,
b111010101111001 "
b111010101111001 *
b111010101111001 3
b1000 5
b1011000 4
1$
#910
0$
#915
0,
b1011001 4
b1011101010111100 "
b1011101010111100 *
b1011101010111100 3
b1001 5
1$
#920
0$
#925
1,
b101110101011110 "
b101110101011110 *
b101110101011110 3
b1010 5
b1011010 4
1$
#930
0$
#935
1,
b1011011 4
b1010111010101111 "
b1010111010101111 *
b1010111010101111 3
b1011 5
1$
#940
0$
#945
1,
b1101011101010111 "
b1101011101010111 *
b1101011101010111 3
b1100 5
b1011100 4
1$
#950
0$
#955
1,
b1011101 4
b1110101110101011 "
b1110101110101011 *
b1110101110101011 3
b1101 5
1$
#960
0$
#965
0,
b1111010111010101 "
b1111010111010101 *
b1111010111010101 3
b1110 5
b1011110 4
1$
#970
0$
#975
1,
b1011111 4
b111101011101010 "
b111101011101010 *
b111101011101010 3
b1111 5
1$
#980
0$
#985
0,
1!
b1011110101110101 "
b1011110101110101 *
b1011110101110101 3
b0 5
b1100000 4
1$
#990
0$
#995
1,
0!
b1100001 4
b101111010111010 "
b101111010111010 *
b101111010111010 3
b1 5
b111 %
1$
#1000
0$
#1005
0,
b1010111101011101 "
b1010111101011101 *
b1010111101011101 3
b10 5
b1100010 4
1$
#1010
0$
#1015
1,
b1100011 4
b101011110101110 "
b101011110101110 *
b101011110101110 3
b11 5
1$
#1020
0$
#1025
0,
b1010101111010111 "
b1010101111010111 *
b1010101111010111 3
b100 5
b1100100 4
1$
#1030
0$
#1035
0,
b1100101 4
b101010111101011 "
b101010111101011 *
b101010111101011 3
b101 5
1$
#1040
0$
#1045
1,
b10101011110101 "
b10101011110101 *
b10101011110101 3
b110 5
b1100110 4
1$
#1050
0$
#1055
1,
b1100111 4
b1001010101111010 "
b1001010101111010 *
b1001010101111010 3
b111 5
1$
#1060
0$
#1065
0,
b1100101010111101 "
b1100101010111101 *
b1100101010111101 3
b1000 5
b1101000 4
1$
#1070
0$
#1075
0,
b1101001 4
b110010101011110 "
b110010101011110 *
b110010101011110 3
b1001 5
1$
#1080
0$
#1085
0,
b11001010101111 "
b11001010101111 *
b11001010101111 3
b1010 5
b1101010 4
1$
#1090
0$
#1095
1,
b1101011 4
b1100101010111 "
b1100101010111 *
b1100101010111 3
b1011 5
1$
#1100
0$
#1105
1,
b1000110010101011 "
b1000110010101011 *
b1000110010101011 3
b1100 5
b1101100 4
1$
#1110
0$
#1115
1,
b1101101 4
b1100011001010101 "
b1100011001010101 *
b1100011001010101 3
b1101 5
1$
#1120
0$
#1125
0,
b1110001100101010 "
b1110001100101010 *
b1110001100101010 3
b1110 5
b1101110 4
1$
#1130
0$
#1135
0,
b1101111 4
b111000110010101 "
b111000110010101 *
b111000110010101 3
b1111 5
1$
#1140
0$
#1145
1,
1!
b11100011001010 "
b11100011001010 *
b11100011001010 3
b0 5
b1110000 4
1$
#1150
0$
#1155
0,
0!
b1110001 4
b1001110001100101 "
b1001110001100101 *
b1001110001100101 3
b1 5
b1000 %
1$
#1160
0$
#1165
1,
b100111000110010 "
b100111000110010 *
b100111000110010 3
b10 5
b1110010 4
1$
#1170
0$
#1175
0,
b1110011 4
b1010011100011001 "
b1010011100011001 *
b1010011100011001 3
b11 5
1$
#1180
0$
#1185
0,
b101001110001100 "
b101001110001100 *
b101001110001100 3
b100 5
b1110100 4
1$
#1190
0$
#1195
1,
b1110101 4
b10100111000110 "
b10100111000110 *
b10100111000110 3
b101 5
1$
#1200
0$
#1205
1,
b1001010011100011 "
b1001010011100011 *
b1001010011100011 3
b110 5
b1110110 4
1$
#1210
0$
#1215
1,
b1110111 4
b1100101001110001 "
b1100101001110001 *
b1100101001110001 3
b111 5
1$
#1220
0$
#1225
1,
b1110010100111000 "
b1110010100111000 *
b1110010100111000 3
b1000 5
b1111000 4
1$
#1230
0$
#1235
0,
b1111001 4
b1111001010011100 "
b1111001010011100 *
b1111001010011100 3
b1001 5
1$
#1240
0$
#1245
1,
b111100101001110 "
b111100101001110 *
b111100101001110 3
b1010 5
b1111010 4
1$
#1250
0$
#1255
1,
b1111011 4
b1011110010100111 "
b1011110010100111 *
b1011110010100111 3
b1011 5
1$
#1260
0$
#1265
b1101111001010011 "
b1101111001010011 *
b1101111001010011 3
b1100 5
b1111100 4
1$
#1270
0$
#1275
0,
b1111101 4
b1110111100101001 "
b1110111100101001 *
b1110111100101001 3
b1101 5
1$
#1280
0$
#1285
1,
b111011110010100 "
b111011110010100 *
b111011110010100 3
b1110 5
b1111110 4
1$
#1290
0$
#1295
1,
b1111111 4
b1011101111001010 "
b1011101111001010 *
b1011101111001010 3
b1111 5
1$
#1300
0$
#1305
0,
1!
b1101110111100101 "
b1101110111100101 *
b1101110111100101 3
b0 5
b10000000 4
1$
#1310
0$
#1315
1,
0!
b10000001 4
b110111011110010 "
b110111011110010 *
b110111011110010 3
b1 5
b1001 %
1$
#1320
0$
#1325
1,
b1011011101111001 "
b1011011101111001 *
b1011011101111001 3
b10 5
b10000010 4
1$
#1330
0$
#1335
0,
b10000011 4
b1101101110111100 "
b1101101110111100 *
b1101101110111100 3
b11 5
1$
#1340
0$
#1345
0,
b110110111011110 "
b110110111011110 *
b110110111011110 3
b100 5
b10000100 4
1$
#1350
0$
#1355
0,
b10000101 4
b11011011101111 "
b11011011101111 *
b11011011101111 3
b101 5
1$
#1360
0$
#1365
1,
b1101101110111 "
b1101101110111 *
b1101101110111 3
b110 5
b10000110 4
1$
#1370
0$
#1375
1,
b10000111 4
b1000110110111011 "
b1000110110111011 *
b1000110110111011 3
b111 5
1$
#1380
0$
#1385
0,
b1100011011011101 "
b1100011011011101 *
b1100011011011101 3
b1000 5
b10001000 4
1$
#1390
0$
#1395
0,
b10001001 4
b110001101101110 "
b110001101101110 *
b110001101101110 3
b1001 5
1$
#1400
0$
#1405
1,
b11000110110111 "
b11000110110111 *
b11000110110111 3
b1010 5
b10001010 4
1$
#1410
0$
#1415
0,
b10001011 4
b1001100011011011 "
b1001100011011011 *
b1001100011011011 3
b1011 5
1$
#1420
0$
#1425
0,
b100110001101101 "
b100110001101101 *
b100110001101101 3
b1100 5
b10001100 4
1$
#1430
0$
#1435
1,
b10001101 4
b10011000110110 "
b10011000110110 *
b10011000110110 3
b1101 5
1$
#1440
0$
#1445
0,
b1001001100011011 "
b1001001100011011 *
b1001001100011011 3
b1110 5
b10001110 4
1$
#1450
0$
#1455
0,
b10001111 4
b100100110001101 "
b100100110001101 *
b100100110001101 3
b1111 5
1$
#1460
0$
#1465
1,
1!
b10010011000110 "
b10010011000110 *
b10010011000110 3
b0 5
b10010000 4
1$
#1470
0$
#1475
1,
0!
b1010 7
b10000000000000000000000000000011 )
b10010001 4
b1001001001100011 "
b1001001001100011 *
b1001001001100011 3
b1 5
b1010 %
1$
